{
  "arquivo": "ca02_30",
  "total": 54,
  "dialogos": [
    {
      "id": 0,
      "personagem": "Futaro",
      "texto_en": "We're arrived, this is it.\\nI wanted to show you this view.",
      "texto_ptbr": ""
    },
    {
      "id": 1,
      "personagem": "Nino",
      "texto_en": "!...",
      "texto_ptbr": ""
    },
    {
      "id": 2,
      "personagem": "Futaro",
      "texto_en": "It's completely different compared to the view\\nfrom the Kouri Bridge,\\nbut it's quite something, isn't it?",
      "texto_ptbr": ""
    },
    {
      "id": 3,
      "personagem": "Nino",
      "texto_en": "Yes...\\nThe ocean, the horizon, the cape, and the sandy beach.\\nThey preserved the natural beauty of the landscape.",
      "texto_ptbr": ""
    },
    {
      "id": 4,
      "personagem": "Nino",
      "texto_en": "Rather than calling it beautiful...\\nLooking at it makes me realize how vast the sea is.\\nEven though it's obvious that the sea is vast.",
      "texto_ptbr": ""
    },
    {
      "id": 5,
      "personagem": "Futaro",
      "texto_en": "I understand what you mean.\\nLooking at this landscape, the word 'majestic' comes to mind.",
      "texto_ptbr": ""
    },
    {
      "id": 6,
      "personagem": "Nino",
      "texto_en": "I didn't know there was such a place.",
      "texto_ptbr": ""
    },
    {
      "id": 7,
      "personagem": "Futaro",
      "texto_en": "This place is called Kafu Banta.\\nIt's a hidden, scenic that's called\\nthe 'Happy Cliff.' It's a power spot.",
      "texto_ptbr": ""
    },
    {
      "id": 8,
      "personagem": "Nino",
      "texto_en": "Happy Cliff?",
      "texto_ptbr": ""
    },
    {
      "id": 9,
      "personagem": "Futaro",
      "texto_en": "Yeah, there's a legend that those who come here\\nwill become happy.",
      "texto_ptbr": ""
    },
    {
      "id": 10,
      "personagem": "Futaro",
      "texto_en": "I thought you would like it.\\nThat's why I brought you here.",
      "texto_ptbr": ""
    },
    {
      "id": 11,
      "personagem": "Nino",
      "texto_en": "Is that so...\\nThank you, Futaro.",
      "texto_ptbr": ""
    },
    {
      "id": 12,
      "personagem": "Futaro",
      "texto_en": "Well, I'm not trying to act like I know everything,\\nbut I actually found out about this place last night.",
      "texto_ptbr": ""
    },
    {
      "id": 13,
      "personagem": "Futaro",
      "texto_en": "I wanted to find a place that would make you happy\\nand be a fitting end to our trip...\\ndo you like it?",
      "texto_ptbr": ""
    },
    {
      "id": 14,
      "personagem": "Nino",
      "texto_en": "Of course.",
      "texto_ptbr": ""
    },
    {
      "id": 15,
      "personagem": "Nino",
      "texto_en": "I'm really happy.\\nFutaro, you looked it up for me...",
      "texto_ptbr": ""
    },
    {
      "id": 16,
      "personagem": "Futaro",
      "texto_en": "......",
      "texto_ptbr": ""
    },
    {
      "id": 17,
      "personagem": "Futaro",
      "texto_en": "Nino.\\nThere's another reason why I brought you here.\\nPlease listen to me.",
      "texto_ptbr": ""
    },
    {
      "id": 18,
      "personagem": "Nino",
      "texto_en": "O-okay.\\nWhat is it?",
      "texto_ptbr": ""
    },
    {
      "id": 19,
      "personagem": "Futaro",
      "texto_en": "I love you, Nino.",
      "texto_ptbr": ""
    },
    {
      "id": 20,
      "personagem": "Nino",
      "texto_en": "......",
      "texto_ptbr": ""
    },
    {
      "id": 21,
      "personagem": "Futaro",
      "texto_en": "From now on, it'll be a long-distance relationship.\\nBut my feelings for you won't change.",
      "texto_ptbr": ""
    },
    {
      "id": 22,
      "personagem": "Futaro",
      "texto_en": "They're feelings brought on\\nby the fact that you entered my life, Nino.",
      "texto_ptbr": ""
    },
    {
      "id": 23,
      "personagem": "Futaro",
      "texto_en": "It's not like a vow...\\nor anything like that, but...",
      "texto_ptbr": ""
    },
    {
      "id": 24,
      "personagem": "Futaro",
      "texto_en": "I want to kiss you.",
      "texto_ptbr": ""
    },
    {
      "id": 25,
      "personagem": "Nino",
      "texto_en": "Huh...?",
      "texto_ptbr": ""
    },
    {
      "id": 26,
      "personagem": "Futaro",
      "texto_en": "Of course I'm not gonna force anything.\\nIf you don't want to, tell me.",
      "texto_ptbr": ""
    },
    {
      "id": 27,
      "personagem": "Futaro",
      "texto_en": "But, if you're alright...",
      "texto_ptbr": ""
    },
    {
      "id": 28,
      "personagem": "Nino",
      "texto_en": "......",
      "texto_ptbr": ""
    },
    {
      "id": 29,
      "personagem": "Futaro",
      "texto_en": "......",
      "texto_ptbr": ""
    },
    {
      "id": 30,
      "personagem": "Nino",
      "texto_en": "Oh come on, that's quite a head-on attack.\\nIt really kills the mood.",
      "texto_ptbr": ""
    },
    {
      "id": 31,
      "personagem": "Futaro",
      "texto_en": "Ggh...",
      "texto_ptbr": ""
    },
    {
      "id": 32,
      "personagem": "Futaro",
      "texto_en": "(Was that too stupidly honest?)",
      "texto_ptbr": ""
    },
    {
      "id": 33,
      "personagem": "Futaro",
      "texto_en": "(Man, I wanted to say something with more atmosphere,\\n but I couldn't think of anything else!)",
      "texto_ptbr": ""
    },
    {
      "id": 34,
      "personagem": "Nino",
      "texto_en": "I think it's actually really bold in a way,\\nbut it's WAY too straightforward.\\nIt was horrid. The worst.",
      "texto_ptbr": ""
    },
    {
      "id": 35,
      "personagem": "Futaro",
      "texto_en": "D-do you have to be so harsh?",
      "texto_ptbr": ""
    },
    {
      "id": 36,
      "personagem": "Nino",
      "texto_en": "But, I like that about you, Futaro.",
      "texto_ptbr": ""
    },
    {
      "id": 37,
      "personagem": "Futaro",
      "texto_en": "!...",
      "texto_ptbr": ""
    },
    {
      "id": 38,
      "personagem": "Nino",
      "texto_en": "It's barely passing as creating a kissing atmosphere,\\nbut for you, Futaro, it's not bad.",
      "texto_ptbr": ""
    },
    {
      "id": 39,
      "personagem": "Futaro",
      "texto_en": "So...is it okay with you?",
      "texto_ptbr": ""
    },
    {
      "id": 40,
      "personagem": "Nino",
      "texto_en": "Stop asking.",
      "texto_ptbr": ""
    },
    {
      "id": 41,
      "personagem": "Futaro",
      "texto_en": "......",
      "texto_ptbr": ""
    },
    {
      "id": 42,
      "personagem": "Nino",
      "texto_en": "......",
      "texto_ptbr": ""
    },
    {
      "id": 43,
      "personagem": "Futaro",
      "texto_en": "(Until now, I've been kissed by Nino,\\n but I've never kissed her myself.)",
      "texto_ptbr": ""
    },
    {
      "id": 44,
      "personagem": "Futaro",
      "texto_en": "(I didn't feel it at that time.\\n The feeling that's bubbling up now is%p-2;――%p;)",
      "texto_ptbr": ""
    },
    {
      "id": 45,
      "personagem": "Futaro",
      "texto_en": "(Maybe it's a feeling of love.)",
      "texto_ptbr": ""
    },
    {
      "id": 46,
      "personagem": "Nino",
      "texto_en": "......",
      "texto_ptbr": ""
    },
    {
      "id": 47,
      "personagem": "Futaro",
      "texto_en": "It's frustrating to barely pass.\\nI'll eventually get a perfect score.",
      "texto_ptbr": ""
    },
    {
      "id": 48,
      "personagem": "Nino",
      "texto_en": "Teehee. My grading system is much harsher\\nthan yours, when you were our tutor, Futaro.",
      "texto_ptbr": ""
    },
    {
      "id": 49,
      "personagem": "Futaro",
      "texto_en": "A higher hurdle makes things more exciting.\\nI'll keep trying until I get a perfect score.",
      "texto_ptbr": ""
    },
    {
      "id": 50,
      "personagem": "Nino",
      "texto_en": "You'll keep trying, huh...",
      "texto_ptbr": ""
    },
    {
      "id": 51,
      "personagem": "Nino",
      "texto_en": "Make sure you get a perfect score\\nby our wedding vow kiss.",
      "texto_ptbr": ""
    },
    {
      "id": 52,
      "personagem": "Futaro",
      "texto_en": "Huh...",
      "texto_ptbr": ""
    },
    {
      "id": 53,
      "personagem": "Nino",
      "texto_en": "Even if it's your first perfect score\\nfrom a vow kiss, I'll forgive you.",
      "texto_ptbr": ""
    }
  ]
}