{
  "arquivo": "ca05_mv5_02",
  "total": 77,
  "dialogos": [
    {
      "id": 0,
      "personagem": "Itsuki",
      "texto_en": "Mmm, this is delicious!\\nChoosing this was the right answer.",
      "texto_ptbr": ""
    },
    {
      "id": 1,
      "personagem": "Miku",
      "texto_en": "Yeah, I can just keep eating this flavor forever. ",
      "texto_ptbr": ""
    },
    {
      "id": 2,
      "personagem": "Futaro",
      "texto_en": "What are you eating?",
      "texto_ptbr": ""
    },
    {
      "id": 3,
      "personagem": "Itsuki",
      "texto_en": "Oh, it's Uesugi-kun.",
      "texto_ptbr": ""
    },
    {
      "id": 4,
      "personagem": "Miku",
      "texto_en": "Taco rice.\\nThey were selling it at the food truck over there.",
      "texto_ptbr": ""
    },
    {
      "id": 5,
      "personagem": "Futaro",
      "texto_en": "...Looks delicious.",
      "texto_ptbr": ""
    },
    {
      "id": 6,
      "personagem": "Itsuki",
      "texto_en": "Uesugi-kun, do you want to eat it too?\\nI won't give you mine, though.",
      "texto_ptbr": ""
    },
    {
      "id": 7,
      "personagem": "Futaro",
      "texto_en": "No need to be so threatening.\\nI won't take yours, so relax.",
      "texto_ptbr": ""
    },
    {
      "id": 8,
      "personagem": "Miku",
      "texto_en": "I won't give you mine either.",
      "texto_ptbr": ""
    },
    {
      "id": 9,
      "personagem": "Futaro",
      "texto_en": "What do you guys think of me...?",
      "texto_ptbr": ""
    },
    {
      "id": 10,
      "personagem": "Miku",
      "texto_en": "Since you're here, why don't you get some too,\\nFutaro?\\nOkinawa has the real stuff.",
      "texto_ptbr": ""
    },
    {
      "id": 11,
      "personagem": "Itsuki",
      "texto_en": "Yes, along with soki soba noodles and goya champuru stir-fry,\\nit's one of the representative dishes of Okinawa.",
      "texto_ptbr": ""
    },
    {
      "id": 12,
      "personagem": "Futaro",
      "texto_en": "Even on Kokusai dori,\\nI saw some stores selling taco rice.",
      "texto_ptbr": ""
    },
    {
      "id": 13,
      "personagem": "Miku",
      "texto_en": "Actually, I didn't know about that\\nuntil I came to Okinawa.",
      "texto_ptbr": ""
    },
    {
      "id": 14,
      "personagem": "Futaro",
      "texto_en": "Really? That's surprising.\\nI thought it was well known.",
      "texto_ptbr": ""
    },
    {
      "id": 15,
      "personagem": "Miku",
      "texto_en": "Well, tacos are Mexican food,\\nso I was wondering if taco rice was also.",
      "texto_ptbr": ""
    },
    {
      "id": 16,
      "personagem": "Itsuki",
      "texto_en": "Heheh, I know the answer here.",
      "texto_ptbr": ""
    },
    {
      "id": 17,
      "personagem": "Itsuki",
      "texto_en": "Tacos are when the ingredients are wrapped in a tortilla.\\nBut%p-2;――",
      "texto_ptbr": ""
    },
    {
      "id": 18,
      "personagem": "Itsuki",
      "texto_en": "The idea of putting those ingredients on rice\\nwas born in Okinawa!",
      "texto_ptbr": ""
    },
    {
      "id": 19,
      "personagem": "Itsuki",
      "texto_en": "Taco rice is a completely new dish\\nthat was created based on Mexican food,\\ntacos, in Okinawa.",
      "texto_ptbr": ""
    },
    {
      "id": 20,
      "personagem": "Miku",
      "texto_en": "I see, that's what it is.",
      "texto_ptbr": ""
    },
    {
      "id": 21,
      "personagem": "Futaro",
      "texto_en": "You know a lot, Itsuki.",
      "texto_ptbr": ""
    },
    {
      "id": 22,
      "personagem": "Itsuki",
      "texto_en": "I studied in advance.\\nIf you want, I can tell you more.",
      "texto_ptbr": ""
    },
    {
      "id": 23,
      "personagem": "Itsuki",
      "texto_en": "Like where it was born in Okinawa,\\nand how it spread!",
      "texto_ptbr": ""
    },
    {
      "id": 24,
      "personagem": "Miku",
      "texto_en": "That's okay for now...",
      "texto_ptbr": ""
    },
    {
      "id": 25,
      "personagem": "Itsuki",
      "texto_en": "*sigh*\\nTalking about them like this,\\nI'm starting to want tacos too.",
      "texto_ptbr": ""
    },
    {
      "id": 26,
      "personagem": "Futaro",
      "texto_en": "Aren't you already eating them?",
      "texto_ptbr": ""
    },
    {
      "id": 27,
      "personagem": "Itsuki",
      "texto_en": "Uesugi-kun? Were you listening to what I said?\\nThis is taco rice, not tacos.",
      "texto_ptbr": ""
    },
    {
      "id": 28,
      "personagem": "Futaro",
      "texto_en": "Well, that's true, but\\nthey're pretty similar, aren't they?",
      "texto_ptbr": ""
    },
    {
      "id": 29,
      "personagem": "Itsuki",
      "texto_en": "Although the flavor profile is similar,\\nthey're completely different dishes!",
      "texto_ptbr": ""
    },
    {
      "id": 30,
      "personagem": "Futaro",
      "texto_en": "O-okay, my bad.",
      "texto_ptbr": ""
    },
    {
      "id": 31,
      "personagem": "Itsuki",
      "texto_en": "You don't think that's the point, do you, Uesugi-kun?\\nPlease pay more attention to food.",
      "texto_ptbr": ""
    },
    {
      "id": 32,
      "personagem": "Futaro",
      "texto_en": "It's hard to take you seriously when you say it like that.",
      "texto_ptbr": ""
    },
    {
      "id": 33,
      "personagem": "Itsuki",
      "texto_en": "What's that supposed to mean?!",
      "texto_ptbr": ""
    },
    {
      "id": 34,
      "personagem": "Miku",
      "texto_en": "...Heheh!",
      "texto_ptbr": ""
    },
    {
      "id": 35,
      "personagem": "Itsuki",
      "texto_en": "Ah...\\nExcuse me, Miku.",
      "texto_ptbr": ""
    },
    {
      "id": 36,
      "personagem": "Miku",
      "texto_en": "No need to apologize.",
      "texto_ptbr": ""
    },
    {
      "id": 37,
      "personagem": "Miku",
      "texto_en": "Itsuki, things are back to normal.\\nI feel relieved.",
      "texto_ptbr": ""
    },
    {
      "id": 38,
      "personagem": "Itsuki",
      "texto_en": "Huh?",
      "texto_ptbr": ""
    },
    {
      "id": 39,
      "personagem": "Miku",
      "texto_en": "Futaro, you feel the same way, right?",
      "texto_ptbr": ""
    },
    {
      "id": 40,
      "personagem": "Futaro",
      "texto_en": "No comment.\\nIf I were to say anything, Itsuki might get angry.",
      "texto_ptbr": ""
    },
    {
      "id": 41,
      "personagem": "Itsuki",
      "texto_en": "Does that mean you're thinking of something\\nthat might make her angry?",
      "texto_ptbr": ""
    },
    {
      "id": 42,
      "personagem": "Futaro",
      "texto_en": "...No comment.",
      "texto_ptbr": ""
    },
    {
      "id": 43,
      "personagem": "Miku",
      "texto_en": "I feel relieved when I see Itsuki enjoying her meals,\\njust like always.",
      "texto_ptbr": ""
    },
    {
      "id": 44,
      "personagem": "Miku",
      "texto_en": "Her smile at those times is a symbol of our peace.",
      "texto_ptbr": ""
    },
    {
      "id": 45,
      "personagem": "Itsuki",
      "texto_en": "I-isn't that a bit too exaggerated...",
      "texto_ptbr": ""
    },
    {
      "id": 46,
      "personagem": "Miku",
      "texto_en": "Yet, it's true. You should also try\\npracticing cooking, instead of just eating.",
      "texto_ptbr": ""
    },
    {
      "id": 47,
      "personagem": "Itsuki",
      "texto_en": "Uungh...\\nI guess I leave the cooking to you and Nino a little too much.",
      "texto_ptbr": ""
    },
    {
      "id": 48,
      "personagem": "Futaro",
      "texto_en": "Yeah, with how prepared she came.\\nItsuki is pretty serious.",
      "texto_ptbr": ""
    },
    {
      "id": 49,
      "personagem": "Miku",
      "texto_en": "That's true, but I think there's one more thing.",
      "texto_ptbr": ""
    },
    {
      "id": 50,
      "personagem": "Futaro",
      "texto_en": "Well, yeah, I'd say it's being able\\nto enjoy food without any worries.",
      "texto_ptbr": ""
    },
    {
      "id": 51,
      "personagem": "Miku",
      "texto_en": "Yeah, that's it. I agree.",
      "texto_ptbr": ""
    },
    {
      "id": 52,
      "personagem": "Itsuki",
      "texto_en": "...I'll take it as a compliment.",
      "texto_ptbr": ""
    },
    {
      "id": 53,
      "personagem": "Miku",
      "texto_en": "I feel relieved when I see Itsuki enjoying her meals,\\njust like always.",
      "texto_ptbr": ""
    },
    {
      "id": 54,
      "personagem": "Miku",
      "texto_en": "Her smile at those times is a symbol of our peace.",
      "texto_ptbr": ""
    },
    {
      "id": 55,
      "personagem": "Itsuki",
      "texto_en": "I-isn't that a bit too exaggerated...",
      "texto_ptbr": ""
    },
    {
      "id": 56,
      "personagem": "Miku",
      "texto_en": "Yet, it's true. You should also try\\npracticing cooking, instead of just eating.",
      "texto_ptbr": ""
    },
    {
      "id": 57,
      "personagem": "Itsuki",
      "texto_en": "Uungh...\\nI guess I leave the cooking to you and Nino a little too much.",
      "texto_ptbr": ""
    },
    {
      "id": 58,
      "personagem": "Futaro",
      "texto_en": "Oh yeah, very relieved.\\nWhen I see Itsuki's eyes shine at the sight of food.",
      "texto_ptbr": ""
    },
    {
      "id": 59,
      "personagem": "Itsuki",
      "texto_en": "Hmm...",
      "texto_ptbr": ""
    },
    {
      "id": 60,
      "personagem": "Itsuki",
      "texto_en": "Ah, I see.\\nThen I feel relieved\\nwhen you start spouting trivia, you know?",
      "texto_ptbr": ""
    },
    {
      "id": 61,
      "personagem": "Futaro",
      "texto_en": "Really now? How about I tell you some Mexican history\\nto go with your taco trivia?",
      "texto_ptbr": ""
    },
    {
      "id": 62,
      "personagem": "Miku",
      "texto_en": "I'll pass. I'll feel like I'm in class.",
      "texto_ptbr": ""
    },
    {
      "id": 63,
      "personagem": "Miku",
      "texto_en": "But it's impressive that you could\\ncounter Futaro like that.",
      "texto_ptbr": ""
    },
    {
      "id": 64,
      "personagem": "Itsuki",
      "texto_en": "Teehee!\\nI haven't just been sitting here\\ngetting talked at, you know.",
      "texto_ptbr": ""
    },
    {
      "id": 65,
      "personagem": "Miku",
      "texto_en": "I feel relieved when I see you enjoying her meals,\\njust like always.",
      "texto_ptbr": ""
    },
    {
      "id": 66,
      "personagem": "Miku",
      "texto_en": "Her smile at those times is a symbol of our peace.",
      "texto_ptbr": ""
    },
    {
      "id": 67,
      "personagem": "Itsuki",
      "texto_en": "I-isn't that a bit too exaggerated...",
      "texto_ptbr": ""
    },
    {
      "id": 68,
      "personagem": "Miku",
      "texto_en": "Yet, it's true. You should also try\\npracticing cooking, instead of just eating.",
      "texto_ptbr": ""
    },
    {
      "id": 69,
      "personagem": "Itsuki",
      "texto_en": "Uungh...\\nI guess I leave the cooking to you and Nino a little too much.",
      "texto_ptbr": ""
    },
    {
      "id": 70,
      "personagem": "Miku",
      "texto_en": "I think there will come a day\\nwhen you want to treat someone to a home-cooked meal.",
      "texto_ptbr": ""
    },
    {
      "id": 71,
      "personagem": "Itsuki",
      "texto_en": "!...",
      "texto_ptbr": ""
    },
    {
      "id": 72,
      "personagem": "Futaro",
      "texto_en": "Wait, what are you talking about?",
      "texto_ptbr": ""
    },
    {
      "id": 73,
      "personagem": "Itsuki",
      "texto_en": "...Yes, you're right. I'll keep that in mind.",
      "texto_ptbr": ""
    },
    {
      "id": 74,
      "personagem": "Futaro",
      "texto_en": "Huh?",
      "texto_ptbr": ""
    },
    {
      "id": 75,
      "personagem": "Miku",
      "texto_en": "Don't worry about it.\\nIt's not about you.",
      "texto_ptbr": ""
    },
    {
      "id": 76,
      "personagem": "Futaro",
      "texto_en": "Nah, that does make me wonder...",
      "texto_ptbr": ""
    }
  ]
}